keplerian/__init__.py
keplerian/keplerian.py
keplerian-0.1.0.dist-info/DESCRIPTION.rst
keplerian-0.1.0.dist-info/METADATA
keplerian-0.1.0.dist-info/RECORD
keplerian-0.1.0.dist-info/WHEEL
keplerian-0.1.0.dist-info/metadata.json
keplerian-0.1.0.dist-info/top_level.txt
