Metadata-Version: 2.0
Name: keplerian
Version: 0.1.0
Summary: A package to calculate the Keplerian function
Home-page: https://github.com/j-faria/keplerian
Author: João Faria
Author-email: joao.faria@astro.up.pt
License: MIT license
Keywords: keplerian
Platform: UNKNOWN
Classifier: Development Status :: 2 - Pre-Alpha
Classifier: Intended Audience :: Developers
Classifier: License :: OSI Approved :: MIT License
Classifier: Natural Language :: English
Classifier: Programming Language :: Python :: 2
Classifier: Programming Language :: Python :: 2.7
Classifier: Programming Language :: Python :: 3
Classifier: Programming Language :: Python :: 3.4
Classifier: Programming Language :: Python :: 3.5
Classifier: Programming Language :: Python :: 3.6
